[
  {
    "_id": 100,
    "name": "Brock Clemons",
    "age": 46,
    "salary": 8723,
    "dept_id": 26,
    "email": "orci.lacus@aliquetlobortis.net"
  },
  {
    "_id": 101,
    "name": "Darrel Knowles",
    "age": 60,
    "salary": 10565,
    "dept_id": 23,
    "email": "risus.Morbi@ligula.co.uk"
  },
  {
    "_id": 102,
    "name": "Vanna Moreno",
    "age": 67,
    "salary": 15417,
    "dept_id": 17,
    "email": "ultrices@eratvitaerisus.com"
  },
  {
    "_id": 103,
    "name": "Yoko Wagner",
    "age": 43,
    "salary": 5273,
    "dept_id": 29,
    "email": "Nunc@Integertinciduntaliquam.net"
  },
  {
    "_id": 104,
    "name": "Reagan Hodge",
    "age": 58,
    "salary": 19317,
    "dept_id": 25,
    "email": "Vivamus@cursus.net"
  },
  {
    "_id": 105,
    "name": "Demetrius Galloway",
    "age": 50,
    "salary": 6703,
    "dept_id": 30,
    "email": "nunc.sit@eget.net"
  },
  {
    "_id": 106,
    "name": "Conan Higgins",
    "age": 26,
    "salary": 17598,
    "dept_id": 16,
    "email": "enim.consequat@vel.net"
  },
  {
    "_id": 107,
    "name": "Igor Spears",
    "age": 69,
    "salary": 10623,
    "dept_id": 19,
    "email": "libero.at@Quisque.edu"
  },
  {
    "_id": 108,
    "name": "Gil Barnett",
    "age": 69,
    "salary": 19723,
    "dept_id": 30,
    "email": "urna.et.arcu@pedeNunc.org"
  },
  {
    "_id": 109,
    "name": "Sonya Hess",
    "age": 55,
    "salary": 7636,
    "dept_id": 18,
    "email": "arcu.imperdiet@velest.edu"
  },
  {
    "_id": 110,
    "name": "Anne Patrick",
    "age": 69,
    "salary": 9867,
    "dept_id": 24,
    "email": "magnis@erosnec.ca"
  },
  {
    "_id": 111,
    "name": "Roary Mcdaniel",
    "age": 62,
    "salary": 15879,
    "dept_id": 13,
    "email": "pede.Nunc@dictum.co.uk"
  },
  {
    "_id": 112,
    "name": "Ora Dickson",
    "age": 77,
    "salary": 9051,
    "dept_id": 23,
    "email": "est@luctusCurabitur.co.uk"
  },
  {
    "_id": 113,
    "name": "Ciara Nichols",
    "age": 31,
    "salary": 8555,
    "dept_id": 17,
    "email": "quis@Aliquamvulputateullamcorper.com"
  },
  {
    "_id": 114,
    "name": "Nichole Sparks",
    "age": 80,
    "salary": 15765,
    "dept_id": 14,
    "email": "molestie@nonluctus.net"
  },
  {
    "_id": 115,
    "name": "Jameson Mclean",
    "age": 68,
    "salary": 19316,
    "dept_id": 29,
    "email": "sem@odio.ca"
  },
  {
    "_id": 116,
    "name": "Fallon Prince",
    "age": 38,
    "salary": 11817,
    "dept_id": 12,
    "email": "Sed.neque.Sed@orci.org"
  },
  {
    "_id": 117,
    "name": "Brenda Albert",
    "age": 28,
    "salary": 10073,
    "dept_id": 12,
    "email": "vel.lectus.Cum@fames.org"
  },
  {
    "_id": 118,
    "name": "Baker Matthews",
    "age": 77,
    "salary": 8465,
    "dept_id": 25,
    "email": "quis.pede.Praesent@Donecfeugiatmetus.org"
  },
  {
    "_id": 119,
    "name": "Wayne White",
    "age": 54,
    "salary": 19866,
    "dept_id": 29,
    "email": "metus.facilisis.lorem@Proinnisl.com"
  },
  {
    "_id": 120,
    "name": "Hasad Cameron",
    "age": 36,
    "salary": 5117,
    "dept_id": 17,
    "email": "pellentesque@SeddictumProin.edu"
  },
  {
    "_id": 121,
    "name": "Colorado Macdonald",
    "age": 59,
    "salary": 5646,
    "dept_id": 12,
    "email": "congue.turpis@placeratorci.org"
  },
  {
    "_id": 122,
    "name": "Cairo Rodgers",
    "age": 34,
    "salary": 18324,
    "dept_id": 21,
    "email": "imperdiet@congue.edu"
  },
  {
    "_id": 123,
    "name": "Colorado Sutton",
    "age": 77,
    "salary": 13909,
    "dept_id": 15,
    "email": "nisi@duiSuspendisseac.ca"
  },
  {
    "_id": 124,
    "name": "Barbara Cardenas",
    "age": 60,
    "salary": 10438,
    "dept_id": 15,
    "email": "tempor@sit.ca"
  },
  {
    "_id": 125,
    "name": "Echo Briggs",
    "age": 70,
    "salary": 9019,
    "dept_id": 22,
    "email": "molestie.orci.tincidunt@magnaPhasellusdolor.co.uk"
  },
  {
    "_id": 126,
    "name": "Molly Mack",
    "age": 35,
    "salary": 5455,
    "dept_id": 10,
    "email": "ligula.Aenean@egestas.net"
  },
  {
    "_id": 127,
    "name": "Odysseus Wilder",
    "age": 33,
    "salary": 19055,
    "dept_id": 18,
    "email": "est@Vestibulum.net"
  },
  {
    "_id": 128,
    "name": "Leroy Brady",
    "age": 73,
    "salary": 11552,
    "dept_id": 17,
    "email": "sit.amet@aliquamarcu.ca"
  },
  {
    "_id": 129,
    "name": "Amal Langley",
    "age": 50,
    "salary": 6087,
    "dept_id": 30,
    "email": "sit@Sednec.org"
  },
  {
    "_id": 130,
    "name": "Quinn Wilkins",
    "age": 33,
    "salary": 5330,
    "dept_id": 23,
    "email": "Quisque.imperdiet.erat@lectusCum.com"
  },
  {
    "_id": 131,
    "name": "Griffin Hickman",
    "age": 43,
    "salary": 6003,
    "dept_id": 19,
    "email": "id.blandit@massaQuisque.edu"
  },
  {
    "_id": 132,
    "name": "Amal Douglas",
    "age": 79,
    "salary": 7354,
    "dept_id": 22,
    "email": "tristique@mattis.co.uk"
  },
  {
    "_id": 133,
    "name": "Kevyn Bradley",
    "age": 54,
    "salary": 11242,
    "dept_id": 19,
    "email": "nascetur@Maecenas.com"
  },
  {
    "_id": 134,
    "name": "Ruby Freeman",
    "age": 40,
    "salary": 14064,
    "dept_id": 16,
    "email": "et.lacinia@arcuVestibulumante.ca"
  },
  {
    "_id": 135,
    "name": "Jennifer Green",
    "age": 26,
    "salary": 14828,
    "dept_id": 30,
    "email": "ridiculus.mus@InloremDonec.net"
  },
  {
    "_id": 136,
    "name": "Alma Ray",
    "age": 50,
    "salary": 6263,
    "dept_id": 13,
    "email": "tristique@velnisl.org"
  },
  {
    "_id": 137,
    "name": "Winifred Doyle",
    "age": 61,
    "salary": 18886,
    "dept_id": 23,
    "email": "orci.Phasellus@purusNullam.edu"
  },
  {
    "_id": 138,
    "name": "Tyrone Hampton",
    "age": 37,
    "salary": 16385,
    "dept_id": 16,
    "email": "a.felis.ullamcorper@dui.ca"
  },
  {
    "_id": 139,
    "name": "Curran Robbins",
    "age": 80,
    "salary": 5545,
    "dept_id": 30,
    "email": "ridiculus@Curabitursed.net"
  },
  {
    "_id": 140,
    "name": "Pandora Gould",
    "age": 78,
    "salary": 16557,
    "dept_id": 15,
    "email": "vel@interdum.co.uk"
  },
  {
    "_id": 141,
    "name": "Tamekah Cross",
    "age": 65,
    "salary": 16121,
    "dept_id": 13,
    "email": "est@sagittis.net"
  },
  {
    "_id": 142,
    "name": "Adrienne Rose",
    "age": 39,
    "salary": 7103,
    "dept_id": 16,
    "email": "parturient@sedest.org"
  },
  {
    "_id": 143,
    "name": "Daryl Townsend",
    "age": 46,
    "salary": 9585,
    "dept_id": 22,
    "email": "sollicitudin@Proin.edu"
  },
  {
    "_id": 144,
    "name": "Mira Mullen",
    "age": 73,
    "salary": 15313,
    "dept_id": 26,
    "email": "leo.Morbi.neque@temporloremeget.ca"
  },
  {
    "_id": 145,
    "name": "Vivien Santos",
    "age": 52,
    "salary": 18813,
    "dept_id": 23,
    "email": "vitae.risus@egestasSed.org"
  },
  {
    "_id": 146,
    "name": "Randall Carpenter",
    "age": 66,
    "salary": 8225,
    "dept_id": 12,
    "email": "mauris@atortorNunc.net"
  },
  {
    "_id": 147,
    "name": "Graiden Mclaughlin",
    "age": 22,
    "salary": 13620,
    "dept_id": 20,
    "email": "tincidunt@mi.edu"
  },
  {
    "_id": 148,
    "name": "Leroy Chen",
    "age": 40,
    "salary": 15930,
    "dept_id": 13,
    "email": "id@NullainterdumCurabitur.net"
  },
  {
    "_id": 149,
    "name": "Benedict Hogan",
    "age": 42,
    "salary": 19926,
    "dept_id": 22,
    "email": "ut.lacus.Nulla@libero.edu"
  },
  {
    "_id": 150,
    "name": "Troy Horton",
    "age": 44,
    "salary": 19517,
    "dept_id": 28,
    "email": "eget.ipsum.Suspendisse@lectus.org"
  },
  {
    "_id": 151,
    "name": "MacKensie Murray",
    "age": 61,
    "salary": 10130,
    "dept_id": 14,
    "email": "Nulla.interdum@NullamenimSed.org"
  },
  {
    "_id": 152,
    "name": "Glenna Bruce",
    "age": 57,
    "salary": 5604,
    "dept_id": 21,
    "email": "enim.Sed.nulla@egetmollislectus.net"
  },
  {
    "_id": 153,
    "name": "Shoshana Cook",
    "age": 79,
    "salary": 16333,
    "dept_id": 21,
    "email": "cubilia@duinecurna.net"
  },
  {
    "_id": 154,
    "name": "Tucker Long",
    "age": 72,
    "salary": 12343,
    "dept_id": 23,
    "email": "Phasellus@eratvolutpat.net"
  },
  {
    "_id": 155,
    "name": "Orli Klein",
    "age": 33,
    "salary": 11904,
    "dept_id": 22,
    "email": "ante.iaculis.nec@hymenaeosMauris.net"
  },
  {
    "_id": 156,
    "name": "Owen Garrett",
    "age": 39,
    "salary": 14533,
    "dept_id": 10,
    "email": "auctor.Mauris@auguemalesuadamalesuada.co.uk"
  },
  {
    "_id": 157,
    "name": "George Potts",
    "age": 33,
    "salary": 15579,
    "dept_id": 24,
    "email": "eu.lacus.Quisque@erat.ca"
  },
  {
    "_id": 158,
    "name": "Alexandra Cook",
    "age": 44,
    "salary": 13188,
    "dept_id": 29,
    "email": "at.libero@arcuVestibulum.net"
  },
  {
    "_id": 159,
    "name": "Hammett Dunlap",
    "age": 48,
    "salary": 10693,
    "dept_id": 12,
    "email": "ipsum@Phasellusvitaemauris.net"
  },
  {
    "_id": 160,
    "name": "Mercedes Garcia",
    "age": 72,
    "salary": 19289,
    "dept_id": 30,
    "email": "fermentum.risus.at@etultricesposuere.edu"
  },
  {
    "_id": 161,
    "name": "Noelle Roy",
    "age": 27,
    "salary": 13930,
    "dept_id": 28,
    "email": "Vestibulum.accumsan@hendreritneque.ca"
  },
  {
    "_id": 162,
    "name": "Deirdre Foreman",
    "age": 47,
    "salary": 15541,
    "dept_id": 23,
    "email": "rutrum.eu@blanditat.com"
  },
  {
    "_id": 163,
    "name": "Georgia Juarez",
    "age": 50,
    "salary": 13626,
    "dept_id": 18,
    "email": "porttitor.eros.nec@Inlorem.co.uk"
  },
  {
    "_id": 164,
    "name": "Jocelyn Lee",
    "age": 78,
    "salary": 5317,
    "dept_id": 14,
    "email": "urna.Nullam.lobortis@lobortisquama.edu"
  },
  {
    "_id": 165,
    "name": "Troy Ramirez",
    "age": 27,
    "salary": 8468,
    "dept_id": 10,
    "email": "pellentesque.massa.lobortis@tellusid.co.uk"
  },
  {
    "_id": 166,
    "name": "Felicia Benjamin",
    "age": 40,
    "salary": 18213,
    "dept_id": 27,
    "email": "imperdiet@neque.com"
  },
  {
    "_id": 167,
    "name": "Quinlan Randolph",
    "age": 72,
    "salary": 13046,
    "dept_id": 13,
    "email": "elementum.purus@orciconsectetuereuismod.co.uk"
  },
  {
    "_id": 168,
    "name": "Eve Orr",
    "age": 57,
    "salary": 18399,
    "dept_id": 23,
    "email": "a@pharetra.edu"
  },
  {
    "_id": 169,
    "name": "Sara Ayala",
    "age": 57,
    "salary": 9470,
    "dept_id": 11,
    "email": "iaculis@nasceturridiculus.com"
  },
  {
    "_id": 170,
    "name": "Stella Bishop",
    "age": 42,
    "salary": 5041,
    "dept_id": 24,
    "email": "Nullam.scelerisque@egestas.edu"
  },
  {
    "_id": 171,
    "name": "Vladimir Brady",
    "age": 30,
    "salary": 18323,
    "dept_id": 11,
    "email": "mauris.sit@elitCurabitursed.net"
  },
  {
    "_id": 172,
    "name": "Lunea Rowe",
    "age": 67,
    "salary": 7517,
    "dept_id": 15,
    "email": "congue.a.aliquet@enimconsequat.ca"
  },
  {
    "_id": 173,
    "name": "Declan Burnett",
    "age": 57,
    "salary": 6796,
    "dept_id": 21,
    "email": "Etiam@semegetmassa.ca"
  },
  {
    "_id": 174,
    "name": "Taylor Colon",
    "age": 80,
    "salary": 9427,
    "dept_id": 10,
    "email": "Sed@velitQuisquevarius.ca"
  },
  {
    "_id": 175,
    "name": "Donovan Griffin",
    "age": 33,
    "salary": 17717,
    "dept_id": 24,
    "email": "libero.Integer.in@interdumNunc.ca"
  },
  {
    "_id": 176,
    "name": "Kitra Cox",
    "age": 66,
    "salary": 17346,
    "dept_id": 12,
    "email": "Aliquam@eudoloregestas.edu"
  },
  {
    "_id": 177,
    "name": "Cedric Alexander",
    "age": 52,
    "salary": 11043,
    "dept_id": 16,
    "email": "auctor.vitae@consectetuereuismodest.ca"
  },
  {
    "_id": 178,
    "name": "Hoyt Miles",
    "age": 63,
    "salary": 9115,
    "dept_id": 21,
    "email": "natoque.penatibus.et@adipiscingelit.edu"
  },
  {
    "_id": 179,
    "name": "Reed Munoz",
    "age": 73,
    "salary": 12097,
    "dept_id": 24,
    "email": "nec@dictumPhasellus.co.uk"
  },
  {
    "_id": 180,
    "name": "Vanna Livingston",
    "age": 72,
    "salary": 6345,
    "dept_id": 30,
    "email": "sit@ipsumprimisin.ca"
  },
  {
    "_id": 181,
    "name": "Victor Suarez",
    "age": 66,
    "salary": 11668,
    "dept_id": 18,
    "email": "Phasellus@inceptoshymenaeosMauris.com"
  },
  {
    "_id": 182,
    "name": "Yoshi Humphrey",
    "age": 50,
    "salary": 15481,
    "dept_id": 21,
    "email": "Curabitur@nec.com"
  },
  {
    "_id": 183,
    "name": "Blaine Hill",
    "age": 74,
    "salary": 5623,
    "dept_id": 11,
    "email": "a.neque.Nullam@dis.co.uk"
  },
  {
    "_id": 184,
    "name": "Patience Sullivan",
    "age": 77,
    "salary": 13128,
    "dept_id": 11,
    "email": "libero.at.auctor@augue.org"
  },
  {
    "_id": 185,
    "name": "Ulysses Velazquez",
    "age": 74,
    "salary": 11632,
    "dept_id": 20,
    "email": "Nunc.laoreet@urnasuscipit.co.uk"
  },
  {
    "_id": 186,
    "name": "Denton Ward",
    "age": 43,
    "salary": 11867,
    "dept_id": 19,
    "email": "nulla.Donec.non@convallisligula.org"
  },
  {
    "_id": 187,
    "name": "Shaine Dotson",
    "age": 54,
    "salary": 16166,
    "dept_id": 13,
    "email": "quam.dignissim.pharetra@aliquet.co.uk"
  },
  {
    "_id": 188,
    "name": "Ramona Butler",
    "age": 54,
    "salary": 5105,
    "dept_id": 11,
    "email": "Nam@tristique.edu"
  },
  {
    "_id": 189,
    "name": "Dean Bush",
    "age": 76,
    "salary": 12908,
    "dept_id": 23,
    "email": "cursus@ametrisus.co.uk"
  },
  {
    "_id": 190,
    "name": "Cecilia Waters",
    "age": 32,
    "salary": 18460,
    "dept_id": 29,
    "email": "parturient@tristiqueaceleifend.com"
  },
  {
    "_id": 191,
    "name": "Adele Wallace",
    "age": 25,
    "salary": 15369,
    "dept_id": 27,
    "email": "pede.ac.urna@acturpis.ca"
  },
  {
    "_id": 192,
    "name": "Kennedy Alston",
    "age": 57,
    "salary": 19159,
    "dept_id": 20,
    "email": "magna.Duis@euodio.com"
  },
  {
    "_id": 193,
    "name": "Alden Cole",
    "age": 33,
    "salary": 8405,
    "dept_id": 19,
    "email": "dui@bibendumullamcorperDuis.org"
  },
  {
    "_id": 194,
    "name": "Hedy Meyers",
    "age": 57,
    "salary": 6549,
    "dept_id": 18,
    "email": "Sed.eget@velit.edu"
  },
  {
    "_id": 195,
    "name": "Bell Garrett",
    "age": 73,
    "salary": 10097,
    "dept_id": 18,
    "email": "est.tempor.bibendum@magna.com"
  },
  {
    "_id": 196,
    "name": "Luke Pate",
    "age": 43,
    "salary": 13583,
    "dept_id": 27,
    "email": "Proin@Nam.org"
  },
  {
    "_id": 197,
    "name": "Colette Torres",
    "age": 68,
    "salary": 16664,
    "dept_id": 24,
    "email": "erat.eget@Inlorem.edu"
  },
  {
    "_id": 198,
    "name": "Heidi Fischer",
    "age": 36,
    "salary": 13561,
    "dept_id": 16,
    "email": "ac.ipsum@mattisCras.com"
  },
  {
    "_id": 199,
    "name": "Raymond Reyes",
    "age": 59,
    "salary": 14452,
    "dept_id": 26,
    "email": "sagittis.lobortis.mauris@duiCumsociis.edu"
  }
]
